LICENSE
MANIFEST.in
NOTICE.md
README.md
SECURITY.md
pyproject.toml
setup.py
lunes_cms/__init__.py
lunes_cms/lunes-cms-cli
lunes_cms.egg-info/PKG-INFO
lunes_cms.egg-info/SOURCES.txt
lunes_cms.egg-info/dependency_links.txt
lunes_cms.egg-info/requires.txt
lunes_cms.egg-info/top_level.txt
lunes_cms/_manifest/spdx_2.2/manifest.spdx.json
lunes_cms/api/__init__.py
lunes_cms/api/apps.py
lunes_cms/api/exception_handler.py
lunes_cms/api/permissions.py
lunes_cms/api/urls.py
lunes_cms/api/utils.py
lunes_cms/api/templates/swagger_ui.html
lunes_cms/api/v1/__init__.py
lunes_cms/api/v1/urls.py
lunes_cms/api/v1/serializers/__init__.py
lunes_cms/api/v1/serializers/alternative_word_serializer.py
lunes_cms/api/v1/serializers/discipline_serializer.py
lunes_cms/api/v1/serializers/document_image_list_serializer.py
lunes_cms/api/v1/serializers/document_image_serializer.py
lunes_cms/api/v1/serializers/document_serializer.py
lunes_cms/api/v1/serializers/fallback_icon_serializer.py
lunes_cms/api/v1/serializers/feedback_serializer.py
lunes_cms/api/v1/serializers/group_serializer.py
lunes_cms/api/v1/serializers/sponsor_serializer.py
lunes_cms/api/v1/serializers/training_set_serializer.py
lunes_cms/api/v1/views/__init__.py
lunes_cms/api/v1/views/discipline_filtered_viewset.py
lunes_cms/api/v1/views/discipline_viewset.py
lunes_cms/api/v1/views/document_by_id_viewset.py
lunes_cms/api/v1/views/document_viewset.py
lunes_cms/api/v1/views/feedback_viewset.py
lunes_cms/api/v1/views/group_viewset.py
lunes_cms/api/v1/views/sponsors_viewset.py
lunes_cms/api/v1/views/training_set_by_id_viewset.py
lunes_cms/api/v1/views/training_set_viewset.py
lunes_cms/api/v1/views/word_viewset.py
lunes_cms/api/v2/__init__.py
lunes_cms/api/v2/urls.py
lunes_cms/api/v2/serializers/__init__.py
lunes_cms/api/v2/serializers/feedback_serializer.py
lunes_cms/api/v2/serializers/job_serializer.py
lunes_cms/api/v2/serializers/sponsor_serializer.py
lunes_cms/api/v2/serializers/unit_serializer.py
lunes_cms/api/v2/serializers/unit_word_relation_serializer.py
lunes_cms/api/v2/serializers/word_serializer.py
lunes_cms/api/v2/views/__init__.py
lunes_cms/api/v2/views/feedback_viewset.py
